katalytic/pkg.py
katalytic_pkg-0.5.0.dist-info/LICENSE.txt
katalytic_pkg-0.5.0.dist-info/WHEEL
katalytic_pkg-0.5.0.dist-info/METADATA
katalytic_pkg-0.5.0.dist-info/RECORD
