Metadata-Version: 2.1
Name: katalytic-pkg
Version: 0.5.0
Summary: This plugin provides some metaprogramming magic for the other katalytic plugins
Keywords: high-level,metaprogramming
Author-email: Valentin Neagu <vali19th@protonmail.com>
Requires-Python: >=3.6
Classifier: Development Status :: 3 - Alpha
Classifier: Intended Audience :: Developers
Classifier: License :: OSI Approved :: MIT License
Classifier: Natural Language :: English
Classifier: Operating System :: OS Independent
Classifier: Programming Language :: Python :: 3
Classifier: Topic :: Software Development :: Libraries
Requires-Dist: pytest ; extra == "dev"
Requires-Dist: pytest-cov ; extra == "dev"
Requires-Dist: pytest-clarity ; extra == "dev"
Requires-Dist: pytest-randomly ; extra == "dev"
Project-URL: homepage, https://gitlab.com/katalytic/katalytic-pkg.git
Project-URL: repository, https://gitlab.com/katalytic/katalytic-pkg.git
Provides-Extra: dev
